dap_conflict2/__init__.py
dap_conflict2/q.py
dap_conflict2-0.1.0.dist-info/DESCRIPTION.rst
dap_conflict2-0.1.0.dist-info/METADATA
dap_conflict2-0.1.0.dist-info/RECORD
dap_conflict2-0.1.0.dist-info/WHEEL
dap_conflict2-0.1.0.dist-info/metadata.json
dap_conflict2-0.1.0.dist-info/top_level.txt
