Metadata-Version: 2.0
Name: dap-conflict2
Version: 0.1.0
Summary: A confict Python package
Home-page: UNKNOWN
Author: Ivan Naumov
Author-email: naumovovr@mail.ru
License: UNKNOWN
Platform: UNKNOWN
Classifier: Development Status :: 1 - Planning
Classifier: Intended Audience :: Science/Research
Classifier: Operating System :: POSIX :: Linux
Classifier: Programming Language :: Python :: 2
Classifier: Programming Language :: Python :: 2.7
Classifier: Programming Language :: Python :: 3
Classifier: Programming Language :: Python :: 3.4
Classifier: Programming Language :: Python :: 3.5
Requires-Dist: numpy (<1.19.0)
Requires-Dist: wheel
